dash_textarea_autocomplete/DashTextareaAutocomplete.py
dash_textarea_autocomplete/__init__.py
dash_textarea_autocomplete/_imports_.py
dash_textarea_autocomplete/dash_textarea_autocomplete.min.js
dash_textarea_autocomplete/dash_textarea_autocomplete.min.js.map
dash_textarea_autocomplete/metadata.json
dash_textarea_autocomplete/package-info.json
dash_textarea_autocomplete-1.3.2.dist-info/LICENSE
dash_textarea_autocomplete-1.3.2.dist-info/METADATA
dash_textarea_autocomplete-1.3.2.dist-info/WHEEL
dash_textarea_autocomplete-1.3.2.dist-info/top_level.txt
dash_textarea_autocomplete-1.3.2.dist-info/RECORD
