Metadata-Version: 2.1
Name: dash-textarea-autocomplete
Version: 1.3.2
Summary: Dash component wrapper for `react-textarea-autocomplete`
Home-page: UNKNOWN
Author: Etienne Tetreault-Pinard <info@etpinard.xyz>
Author-email: UNKNOWN
License: MIT
Platform: UNKNOWN
Classifier: Framework :: Dash
